nyaaup/__init__.py
nyaaup/auth.py
nyaaup/up.py
nyaaup/utils/__init__.py
nyaaup/utils/auth.py
nyaaup/utils/collections.py
nyaaup/utils/databases.py
nyaaup/utils/logging.py
nyaaup/utils/mediainfo.py
nyaaup/utils/torrent.py
nyaaup/utils/upload.py
nyaaup/utils/uploader.py
nyaaup/utils/userconfig.py
nyaaup-6.1.0.dist-info/METADATA
nyaaup-6.1.0.dist-info/WHEEL
nyaaup-6.1.0.dist-info/entry_points.txt
nyaaup-6.1.0.dist-info/licenses/LICENSE
nyaaup-6.1.0.dist-info/RECORD
