Metadata-Version: 2.4
Name: nyaaup
Version: 6.1.0
Summary: Auto uploader to Nyaa
Project-URL: homepage, https://github.com/varyg1001/nyaaup
Project-URL: Changelog, https://github.com/varyg1001/nyaaup/blob/main/changelog.md
Author: varyg
License:                     GNU GENERAL PUBLIC LICENSE
License-File: LICENSE
Requires-Python: <3.14,>=3.10
Requires-Dist: aiofiles<25.0.0,>=24.1.0
Requires-Dist: click<9.0.0,>=8.1.3
Requires-Dist: cloup<4.0.0,>=3.0.5
Requires-Dist: httpx<0.28.0,>=0.27.0
Requires-Dist: humanize<5.0.0,>=4.4.0
Requires-Dist: langcodes<4.0.0,>=3.3.0
Requires-Dist: language-data<2.0,>=1.1
Requires-Dist: mal-api<0.6.0,>=0.5.2
Requires-Dist: platformdirs<5.0.0,>=4.0.0
Requires-Dist: pymal<0.7,>=0.6
Requires-Dist: pymediainfo<8.0.0,>=7.0.0
Requires-Dist: pyoxipng<10.0.0,>=9.0.0
Requires-Dist: rich<14.0.0,>=13.0.0
Requires-Dist: ruamel-yaml<0.19.0,>=0.18.0
Requires-Dist: tls-client2<2.0.0,>=1.1.0
Requires-Dist: torf<5.0.0,>=4.0.4
Requires-Dist: typing-extensions<5.0.0,>=4.11.0
Requires-Dist: wand<0.7.0,>=0.6.10
Provides-Extra: dev
Requires-Dist: isort<6.0.0,>=5.9.2; extra == 'dev'
Requires-Dist: ruff<0.2.0,>=0.1.14; extra == 'dev'
